[
  {
    "date": "背景 (2022 起轉型)",
    "source": "優分析 UAnalyze",
    "url": "https://uanalyze.com.tw/articles/3750112290",
    "title": "宇隆=汽車精密零件廠(噴油嘴等),2022 起推自有品牌 TUF One 行星減速機,並開發諧波/RV 減速機,朝機器人關節/自動化延伸(減速機轉型故事早已存在)",
    "excerpt": "宇隆為精密金屬零件加工廠(汽車噴油嘴等),2022 年推自有品牌 TUF One 行星減速機,積極開發諧波、RV 減速機,朝機器人關節與自動化延伸。t0(2023-11-20)前『減速機轉型』故事已存在多時,為機器人供應鏈的潛在受惠者,但當時屬遠期想像。",
    "pit": "pre_t0",
    "pricing_state": "已知轉型故事 (潛在受惠,催化未到)",
    "used": true
  },
  {
    "date": "2023-11 (漲勢)",
    "source": "CMoney / Goodinfo",
    "url": "https://www.cmoney.tw/forum/stock/2233",
    "title": "2023 年 11 月宇隆股價走揚(t0 前 120 日 +38%),搭減速機/機器人題材+法人短線買盤;正逢 2023-11 台股 AI 反彈波,含明顯 beta 成分",
    "excerpt": "2023-11 宇隆股價走揚,t0(11/20)前 120 日漲幅 +38%,題材為減速機切機器人關節+法人短線回補買盤,並正逢 2023 年 11 月台股在 AI 帶動下的反彈波(大盤 beta)。但當時人形機器人尚未有硬催化點火,漲勢為題材搶跑+beta,缺乏即時的訂單/事件支撐。",
    "pit": "pre_t0",
    "pricing_state": "題材搶跑+beta (無硬催化)",
    "used": true
  },
  {
    "date": "催化時序 (對照)",
    "source": "維基 / 特斯拉事件 / 既有 2233 檔案",
    "url": "https://zh.wikipedia.org/zh-tw/Optimus_(%E6%A9%9F%E5%99%A8%E4%BA%BA)",
    "title": "人形機器人真正點火在 2024:特斯拉 Optimus Gen-2(2023-12 底)、We, Robot 發表會(2024-10);宇隆的成功大行情落在 2024-10(Tesla 事件搶跑),非 2023-11",
    "excerpt": "人形機器人供應鏈的真正點火催化在 2024:特斯拉 Optimus Gen-2 於 2023-12 底亮相、We, Robot 發表會於 2024-10 舉行。宇隆的成功大行情落在 2024-10(見既有檔 2233_2024-10-09,Tesla 事件搶跑+族群共振)。t0(2023-11-20)這波提前約 11 個月,催化尚未到位,故 60 日僅 +5% 後回落。",
    "pit": "post_t0",
    "pricing_state": "遠期催化 (真正點火在 2024,提前約 11 個月)",
    "used": true
  },
  {
    "date": "事後鋪陳",
    "source": "MoneyDJ / 優分析",
    "url": "https://www.moneydj.com/kmdj/news/newsviewer.aspx?a=c4698d57-18de-4724-895d-c93980f683e9",
    "title": "(事後)2024-06 宇隆台中新廠啟用(斥資 10 億、產能 3x)為 TUF One 減速機主基地;諧波/RV 減速機、Tesla Optimus BOM 想像等深度敘事均為 2024~2025",
    "excerpt": "(事後)2024-06 宇隆台中港新廠啟用(斥資 10 億、產能 3 倍)為 TUF One 減速機主研發生產基地;諧波/RV 減速機打入 Optimus Gen-3(諧波用量 12→54)、與信邦 MOU 等深度人形機器人敘事均為 2024~2025。t0(2023-11)當時這些鋪陳與催化都尚未發生,印證前期漲勢是題材搶跑而非事件驅動。",
    "pit": "post_t0",
    "pricing_state": "事後 (產能/深度敘事鋪陳於 2024-25)",
    "used": true
  }
]
