[
  {
    "date": "2023-05-12",
    "source": "鉅亨網 (cnyes id 5177350) / 經濟日報 (udn 7166964)",
    "url": "https://news.cnyes.com/news/id/5177350",
    "title": "台灣銘板與幣託(BitoPro)簽 NFC 冷錢包(FortVax)供應合約,合約總額最高 7000 萬元",
    "excerpt": "台灣銘板(6593)與幣託科技簽 NFC 冷錢包供應合約,每次最少訂購 5 萬張,合約總金額最高達 240 萬美元(逾新台幣 7000 萬元),採訂閱式商業模式。董事長劉立恩:『象徵 2023 年為台灣銘板正式進軍區塊鏈市場布局的元年』。幣託累積會員 80 萬、台灣 9 成市占。此加密貨幣冷錢包題材於 t0(8/16)前 3 個月即公開,屬醞釀型種子。",
    "pit": "pre_t0",
    "pricing_state": "部分反應(題材已公開,股價尚未大漲)",
    "used": true
  },
  {
    "date": "2022-07-04",
    "source": "TechNews 科技新報",
    "url": "https://finance.technews.tw/2022/07/04/fortvax/",
    "title": "FortVax 連線僅 5 秒防駭,誠研攜手台灣銘板推個人化冷錢包",
    "excerpt": "台灣銘板(VISA/MASTERCARD 授權製造商)與誠研、香港區塊鏈商合作,歷經逾一年研發,2022 年量產 FortVax NFC 冷錢包——私鑰離線儲存、信用卡尺寸、低碳低價。此為冷錢包產品最初的題材種子(t0 前逾一年),奠定後續加密貨幣故事。",
    "pit": "pre_t0",
    "pricing_state": "尚未反應(產品早期種子,t0 前逾一年)",
    "used": true
  },
  {
    "date": "背景(2023 上半年基本面轉機醞釀中)",
    "source": "財報狗 / 聯合新聞網 (2023 年報回顧,udn 7793784)",
    "url": "https://statementdog.com/analysis/6593/monthly-revenue",
    "title": "台灣銘板 2023 卡片業務(含冷錢包)大幅轉強,毛利率與獲利跳升",
    "excerpt": "台灣銘板 2023 全年營收 6.68 億元(+28.6%),卡片(含冷錢包)占 71.4%、年增 33.6%,毛利率由 2022 的 21.0% 升至 30.0%,稅後淨利年增 1711%、EPS 2.08 元(+1633%)為近 5 年最佳。驅動來自支付卡需求、觀光復甦、銀行換卡潮、聯名/綠色信用卡,加上 FortVax 限量冷錢包自 9 月起分批出貨。t0=8/16 正逢 H1(Q2)財報公布窗口(8/14 截止),基本面轉機於此時被市場看見。",
    "pit": "pre_t0",
    "pricing_state": "反應中(t0 恰逢半年報轉機顯現)",
    "used": true
  },
  {
    "date": "2023-09 起(事後)",
    "source": "公司年報 / 券商整理",
    "url": "https://www.taiwannameplate.com/FortVax/index.html",
    "title": "[事後] FortVax 限量版 NFC 冷錢包自 2023 年 9 月起分批出貨",
    "excerpt": "限量版 NFC 冷錢包 FortVax 訂單自 2023 年 9 月起分階段出貨,挹注卡片營收。此出貨時點在 t0(8/16)之後,屬事後實現的營收驅動,佐證加密貨幣題材由概念走向落地。",
    "pit": "post_t0",
    "pricing_state": "事後(題材落地出貨)",
    "used": true
  },
  {
    "date": "2024-03 前後(事後回顧)",
    "source": "聯合新聞網 (udn 7793784)",
    "url": "https://udn.com/news/story/7254/7793784",
    "title": "[事後] 台灣銘板財報:2023 年 EPS 2.08 元、年增 1633%",
    "excerpt": "台灣銘板 2023 全年 EPS 2.08 元、年增 1,633%,稅後淨利年增 1,711%,擬配現金股利 1 元。此為 t0 後數月的完整年報確認,回頭驗證了 2023 全年的獲利爆發。",
    "pit": "post_t0",
    "pricing_state": "事後確認(全年財報)",
    "used": true
  }
]
