[{"code": "2317", "name": "鴻海", "industry": "其他電子業", "t0": "2024-02-29", "gain_60d": 0.8, "rev_yoy_12m_before": [48.1, -11.6, -21.1, -11.8, -9.5, -19.7, -1.2, -8.0, -19.6, -4.6, 18.0, -26.9], "price_120d_before_norm100": [102.9, 104.4, 101.0, 104.4, 95.3, 94.4, 98.5, 98.5, 100.5, 98.5, 97.0, 98.5, 100.0], "price_60d_after_norm100": [99.0, 101.9, 128.2, 141.3, 145.6, 153.4, 136.9, 139.8, 151.5, 164.6, 165.5, 164.1], "chips": {"外資20日淨買佔成交%": 6.2, "外資60日": -5.3, "投信20日": -0.7, "投信60日": 3.8, "融資20日Δ%": -5.0, "融資60日Δ%": -20.3, "借券20日Δ%": -5.8, "外資持股%": 38.2}, "valuation": {"PE": 11.1, "PB": 1.0, "殖利率%": 5.1, "PE三年分位%": 62.6, "PB三年分位%": 16.5}, "financials": {"近4季累計毛利率%": [6.0, 6.0, 6.2, 6.4], "近4季累計營益率%": [2.6, 2.8, 2.6, 2.7]}, "corp_events": {"內部人申讓筆數_180日": 0, "庫藏股公告_180日": 0, "減資_365日": 0}}, {"code": "2464", "name": "盟立", "industry": "其他電子業", "t0": "2024-02-27", "gain_60d": 0.81, "rev_yoy_12m_before": [-13.9, -9.0, -2.4, -16.9, -31.6, -26.7, -18.5, -20.4, -4.2, -29.8, -22.3, -20.9], "price_120d_before_norm100": [102.8, 106.0, 102.4, 102.1, 102.3, 97.9, 97.0, 95.8, 95.1, 94.8, 94.7, 95.2, 100.0], "price_60d_after_norm100": [101.1, 103.8, 102.3, 110.5, 124.5, 129.5, 127.7, 115.5, 131.7, 129.5, 131.3, 147.8], "chips": {"外資20日淨買佔成交%": -2.9, "外資60日": -3.4, "投信20日": -0.6, "投信60日": -0.5, "融資20日Δ%": 20.9, "融資60日Δ%": 2.4, "借券20日Δ%": 11.2, "外資持股%": 2.8}, "valuation": {"PE": 137.1, "PB": 1.9, "殖利率%": 4.7, "PE三年分位%": 99.9, "PB三年分位%": 44.6}, "financials": {"近4季累計毛利率%": [17.4, 16.0, 17.2, 17.0], "近4季累計營益率%": [3.3, 1.8, 0.7, 0.5]}, "corp_events": {"內部人申讓筆數_180日": 0, "庫藏股公告_180日": 0, "減資_365日": 0}}, {"code": "6530", "name": "創威", "industry": "通信網路業", "t0": "2024-07-22", "gain_60d": 0.82, "rev_yoy_12m_before": [-6.5, -5.3, 2.4, -2.8, -3.2, 2.8, -20.9, 42.0, 39.8, -6.9, 2.7, 0.5], "price_120d_before_norm100": [95.2, 107.3, 117.8, 113.9, 111.4, 107.1, 101.1, 100.2, 104.6, 98.8, 108.3, 105.2, 100.0], "price_60d_after_norm100": [101.0, 98.0, 86.1, 87.9, 97.5, 99.8, 110.4, 134.8, 130.6, 135.9, 172.2, 180.0], "chips": {"外資20日淨買佔成交%": -1.5, "外資60日": -0.1, "投信20日": 0.0, "投信60日": 0.0, "融資20日Δ%": -0.2, "融資60日Δ%": -2.2, "借券20日Δ%": 68.9, "外資持股%": 1.3}, "valuation": {"PE": 34.5, "PB": 3.5, "殖利率%": 2.4, "PE三年分位%": 84.3, "PB三年分位%": 83.9}, "financials": {"近4季累計毛利率%": [41.3, 42.7, 42.9, 42.3], "近4季累計營益率%": [18.0, 18.8, 19.2, 16.6]}, "corp_events": {"內部人申讓筆數_180日": 0, "庫藏股公告_180日": 0, "減資_365日": 0}}, {"code": "2233", "name": "宇隆", "industry": "汽車工業", "t0": "2024-10-09", "gain_60d": 0.82, "rev_yoy_12m_before": [13.6, 15.7, 16.7, 18.2, 43.6, -8.1, 0.4, 25.0, 15.1, 15.3, 28.1, -2.3], "price_120d_before_norm100": [84.2, 81.9, 87.1, 86.5, 85.8, 90.0, 90.6, 84.5, 83.5, 91.6, 108.7, 110.0, 100.0], "price_60d_after_norm100": [100.6, 98.4, 108.7, 101.0, 103.5, 97.1, 127.1, 113.2, 115.2, 114.5, 147.4, 172.6], "chips": {"外資20日淨買佔成交%": -0.7, "外資60日": -1.7, "投信20日": 0.2, "投信60日": 0.2, "融資20日Δ%": -24.4, "融資60日Δ%": 17.9, "借券20日Δ%": -1.2, "外資持股%": 12.1}, "valuation": {"PE": 15.2, "PB": 2.6, "殖利率%": 3.3, "PE三年分位%": 82.8, "PB三年分位%": 96.3}, "financials": {"近4季累計毛利率%": [31.5, 32.7, 35.2, 36.7], "近4季累計營益率%": [15.5, 15.9, 18.7, 19.4]}, "corp_events": {"內部人申讓筆數_180日": 0, "庫藏股公告_180日": 0, "減資_365日": 0}}, {"code": "8440", "name": "綠電", "industry": "綠能環保", "t0": "2024-06-04", "gain_60d": 0.82, "rev_yoy_12m_before": [0.6, 22.3, 5.6, 10.4, 8.1, 7.5, 8.3, -3.3, 35.2, -15.3, -11.3, 23.8], "price_120d_before_norm100": [89.0, 92.6, 92.8, 97.3, 92.8, 100.1, 97.9, 99.7, 99.0, 107.5, 110.6, 107.6, 100.0], "price_60d_after_norm100": [101.9, 100.3, 103.6, 142.5, 174.3, 172.8, 150.8, 152.2, 139.0, 148.4, 148.8, 154.9], "chips": {"外資20日淨買佔成交%": -1.0, "外資60日": -0.7, "投信20日": 0.0, "投信60日": 0.0, "融資20日Δ%": -6.3, "融資60日Δ%": 17.1, "借券20日Δ%": 32.4, "外資持股%": 0.7}, "valuation": {"PE": 50.1, "PB": 2.4, "殖利率%": 4.3, "PE三年分位%": 79.8, "PB三年分位%": 48.3}, "financials": {"近4季累計毛利率%": [11.9, 11.8, 11.2, 7.3], "近4季累計營益率%": [5.4, 5.8, 5.1, 0.9]}, "corp_events": {"內部人申讓筆數_180日": 0, "庫藏股公告_180日": 0, "減資_365日": 0}}, {"code": "5386", "name": "青雲", "industry": "電腦及週邊設備業", "t0": "2024-01-17", "gain_60d": 0.82, "rev_yoy_12m_before": [-61.9, -73.5, -52.3, -67.2, -65.2, -28.3, -16.3, -7.7, -24.3, -18.0, 70.4, -34.9], "price_120d_before_norm100": [134.6, 109.9, 101.6, 102.6, 101.4, 99.6, 99.8, 102.8, 107.9, 116.2, 108.5, 109.1, 100.0], "price_60d_after_norm100": [99.8, 102.0, 97.8, 107.7, 102.2, 116.2, 155.9, 170.4, 177.5, 179.1, 144.7, 140.1], "chips": {"外資20日淨買佔成交%": -2.0, "外資60日": -0.3, "投信20日": 0.0, "投信60日": 0.0, "融資20日Δ%": -6.7, "融資60日Δ%": -14.9, "借券20日Δ%": 8.3, "外資持股%": 0.2}, "valuation": {"PE": 27.3, "PB": 3.1, "殖利率%": 1.9, "PE三年分位%": 64.3, "PB三年分位%": 70.9}, "financials": {"近4季累計毛利率%": [5.7, 8.9, 6.4, 5.9], "近4季累計營益率%": [2.9, 4.2, 2.8, 2.1]}, "corp_events": {"內部人申讓筆數_180日": 0, "庫藏股公告_180日": 0, "減資_365日": 0}}, {"code": "2489", "name": "瑞軒", "industry": "光電業", "t0": "2024-04-18", "gain_60d": 0.82, "rev_yoy_12m_before": [-30.7, 7.3, -9.2, -31.4, 33.9, 33.8, 18.5, 33.3, 11.4, 26.8, 41.6, 6.4], "price_120d_before_norm100": [82.5, 81.1, 81.4, 83.9, 89.8, 90.9, 95.1, 93.7, 108.8, 103.2, 96.5, 101.1, 100.0], "price_60d_after_norm100": [97.5, 106.7, 105.6, 112.6, 127.0, 143.2, 145.6, 135.8, 137.2, 140.0, 144.6, 148.1], "chips": {"外資20日淨買佔成交%": 6.9, "外資60日": 1.4, "投信20日": 0.0, "投信60日": 0.0, "融資20日Δ%": 2.9, "融資60日Δ%": 34.1, "借券20日Δ%": -22.4, "外資持股%": 12.9}, "valuation": {"PE": 24.0, "PB": 0.8, "殖利率%": 3.8, "PE三年分位%": 91.2, "PB三年分位%": 80.0}, "financials": {"近4季累計毛利率%": [9.8, 9.1, 9.5, 9.6], "近4季累計營益率%": [-0.3, -1.0, -0.3, -0.1]}, "corp_events": {"內部人申讓筆數_180日": 0, "庫藏股公告_180日": 0, "減資_365日": 1}}, {"code": "3030", "name": "德律", "industry": "其他電子業", "t0": "2024-02-05", "gain_60d": 0.82, "rev_yoy_12m_before": [-64.4, -43.2, -10.8, -47.9, -48.8, -50.5, -42.5, -28.2, -31.1, -52.2, -34.4, 104.7], "price_120d_before_norm100": [84.8, 84.9, 89.5, 87.6, 89.2, 86.4, 87.6, 89.1, 88.8, 88.5, 96.7, 97.3, 100.0], "price_60d_after_norm100": [101.1, 100.1, 104.9, 109.6, 111.9, 116.1, 125.7, 125.6, 139.8, 131.5, 152.3, 170.3], "chips": {"外資20日淨買佔成交%": 13.2, "外資60日": 14.4, "投信20日": -0.0, "投信60日": -0.0, "融資20日Δ%": 11.7, "融資60日Δ%": 51.7, "借券20日Δ%": -37.5, "外資持股%": 17.4}, "valuation": {"PE": 15.9, "PB": 2.4, "殖利率%": 6.4, "PE三年分位%": 99.9, "PB三年分位%": 81.3}, "financials": {"近4季累計毛利率%": [57.4, 60.8, 59.2, 59.3], "近4季累計營益率%": [32.1, 29.9, 26.0, 25.5]}, "corp_events": {"內部人申讓筆數_180日": 0, "庫藏股公告_180日": 0, "減資_365日": 0}}]