[
  {
    "date": "2025-01-07",
    "source": "鉅亨網 cnyes",
    "url": "https://news.cnyes.com/news/id/5828426",
    "title": "〈CES 2025〉黃仁勳高喊實體AI時代已到來 欽點廣運(6125)、和碩(4938)、所羅門(2359)三家台廠",
    "excerpt": "2025-01-07 CES 2025 黃仁勳 keynote,於 Omniverse 數位孿生 + Cosmos 實體AI 平台簡報背板具名點名三家台廠:廣運(6125)、和碩(4938)列為『解決方案與服務供應商』,所羅門(2359)列為『機器人與感測器供應商』。黃強調 Omniverse+Cosmos 為全球實體產業數位化基礎函式庫,用於工廠、倉儲、運送場景。此為 t0(2025-01-13) 前、可審計、具名的旗艦事件供應鏈點名(signal type 2),WebFetch 核實發布日 2025-01-07。是廣運本次標記的主錨催化。",
    "used": true
  },
  {
    "date": "2025-01-07",
    "source": "鉅亨網 cnyes",
    "url": "https://news.cnyes.com/news/id/5828201",
    "title": "〈CES 2025〉黃仁勳主題演說:輝達推出機器人訓練技術(Isaac GR00T Blueprint/Cosmos)與新遊戲晶片(RTX 50)",
    "excerpt": "2025-01-07 黃仁勳 CES 主題演說發表 Cosmos 世界基礎模型(理解物理法則、生成合成訓練資料)、Isaac GR00T Blueprint(加速人形機器人開發)、RTX 50 系列。定調『實體AI(Physical AI)』時代,估人形機器人市場長線 380 億美元。此為 2025-01 台股人形機器人/實體AI 供應鏈題材『第二次點火』的旗艦事件錨(第一次為 2024-10 特斯拉 We,Robot)。PIT ≤2025-01-13。",
    "used": true
  },
  {
    "date": "2025-01-08",
    "source": "經濟日報 money.udn",
    "url": "https://money.udn.com/money/story/5599/8474576",
    "title": "整理包／黃仁勳旋風來了！CES 演講五大重點、點名最新台廠供應商一次看",
    "excerpt": "2025-01-08 經濟日報整理包彙整黃仁勳 CES 2025 五大重點(Cosmos、RTX 50、Project DIGITS、實體AI/機器人、車用),並列出簡報背板點名的台廠供應鏈(廣運、和碩、所羅門等)。作為 CES 台廠 read-through 的權威彙整,佐證『旗艦事件供應鏈傳導』題材在 2025-01 上旬點火。story id 8474576 與同期 CES 報導群(8473605/8478816)一致落於 2025-01 上旬,PIT ≤2025-01-13。",
    "used": true
  },
  {
    "date": "2025-01-07",
    "source": "TechNews 科技新報",
    "url": "https://technews.tw/2025/01/07/nvidia-launches-project-digits-with-mediatek-chips/",
    "title": "AI 超級電腦放進口袋,輝達攜手聯發科推出 Project DIGITS(GB10 由聯發科共同設計)",
    "excerpt": "2025-01-07 輝達 CES 發表個人 AI 超級電腦 Project DIGITS,搭載 GB10 Grace Blackwell 超級晶片,其 20 核 Arm CPU 由聯發科(2454)共同設計(『教主唯一欽點』),128GB 統一記憶體,2025-05 上市、售價 3,000 美元起。聯發科為 CES 2025 直接具名 read-through、當期營收成長。惟聯發科為兆元 mega-cap、GB10/DIGITS 營收占比甚小且點名當日即人盡皆知,大幅上漲空間受限,本次列 watchlist(conviction 3)未標記。PIT ≤2025-01-13。",
    "used": false
  },
  {
    "date": "2024-10-10",
    "source": "特斯拉 We,Robot 發表會 / 維基百科(庫內 ev27_news/2233_2024-10-09.json)",
    "url": "https://zh.wikipedia.org/zh-tw/Optimus_(%E6%A9%9F%E5%99%A8%E4%BA%BA)",
    "title": "特斯拉 'We, Robot' 發表會(Optimus 人形機器人)點火全球機器人供應鏈,台股減速機/傳動廠(上銀2049、大銀4576、和大1536、宇隆2233)齊漲",
    "excerpt": "2024-10-10(美)/10-11(台)特斯拉 We,Robot 展示 Optimus/Cybercab,點燃全球人形機器人供應鏈行情;台股減速機/傳動族群(上銀、大銀、和大、宇隆)同步走強、卡位出貨。為 2025-01 CES 實體AI 再點火前的『第一次點火』。此材料取自本地庫 ev27_news/2233_2024-10-09.json 之 pre_t0 段(PIT ≤2024-10)。注意:同檔另引 money.udn/9265985(『準備出貨』)其 story id(9.27M) 遠高於 CES 群(8.47M),應為 2025 年中後文章、係策展 recency 誤植,本次不採用。上銀為此題材之滾珠螺桿/線性滑軌+減速機直接環節龍頭。",
    "used": true
  },
  {
    "date": "2025-01(2024 全年營收公佈)",
    "source": "聯合新聞網 / 經濟日報(udn 8478504,搜尋快照;原頁現 404)",
    "url": "https://udn.com/news/story/7252/8478504",
    "title": "上銀(2049) 2024 年營收微減、法人估全年 EPS 近 6 元;工具機/半導體設備景氣落底、2025 估年增約 12.77%",
    "excerpt": "2024 全年營收公佈(約 2025-01 上旬):上銀 2024 營收年減約 0.9%(近乎持平),終結『連續七季衰退』,判為循環谷底;法人估 2025 營收年增約 12.77%、成長動能來自半導體長期擴產與 AI 機器人/自動化。此為上銀『谷底翻揚』(非仍在下滑)之 PIT 佐證,避開『當期營收下滑+本夢比』一票否決。原文頁現 404,內容取自 2025-01 搜尋快照(標題與法人數字)。",
    "used": true
  },
  {
    "date": "2024(全年財報,約 2025-01 前後公佈)",
    "source": "台股財務資料彙整(nStock/阿股達 6125 營收頁 + 產業報導)",
    "url": "https://www.nstock.tw/%E5%BB%A3%E9%81%8B%E5%81%9A%E4%BB%80%E9%BA%BC.html",
    "title": "廣運(6125)2024 營收降至 26.97 億係『金運科技(散熱事業)分割』之一次性認列變動;H2 營運明顯改善、Q4 近損益兩平",
    "excerpt": "廣運 2024 營收驟降近半至 26.97 億、EPS -0.56,主因將熱傳散熱事業重組切分移轉子公司金運科技(財報認列口徑變動)+半導體客戶拉貨時程,屬『一次性調整』非長期營運趨勢;2024 下半年營運已明顯改善、單 Q4 接近損益兩平。此為判定廣運當期衰退屬『組織重整/口徑』而非需求崩壞的關鍵——與所羅門(2359)之有機 -17% 下滑不同,故廣運可標記、所羅門列 watchlist。廣運資料中心液冷方案已獲廣達/緯創/鴻海採用、半導體廠務自動化受惠先進封裝擴產(直接環節,非蹭貼)。",
    "used": true
  },
  {
    "date": "2024(2024 全年營收 -16.99%)",
    "source": "台股財務資料(所羅門 2359)/CES 報導",
    "url": "https://info.ifa.ai/tw-stock/2359/finance-overview",
    "title": "[watchlist,未標記] 所羅門(2359)雖獲黃仁勳 CES 點名,但 2024 全年營收年減約 17%(有機下滑);能源/發電機訂單爆發為 2025 Q1 後之 post-PIT 事實",
    "excerpt": "所羅門 2024 營收約 35.05 億、年減約 17%(材料代理業務走弱之有機下滑)。其後使其成星的『AI 資料中心發電機(Kohler 代理)訂單 20-25 億躍升』為 2025 Q1 揭露(post-PIT),於 t0(2025-01-13)不可見。依 signal type 2 排除準則『純題材想像而當期基本面反衰退』,個股獲旗艦點名但當期營收有機年減+近端數字接棒尚未確認者列 watchlist(conviction 3),不標記——體現『寧可漏一個真的』紀律。此筆為說明放棄理由,used=false。",
    "used": false
  },
  {
    "date": "2025-01-16(post-PIT,不可用為 t0 前催化)",
    "source": "庫內 ev27_news/6442_2025-05-05.json + 3081_2025-06-05.json(CPO 題材時齡佐證)",
    "url": "https://news.cnyes.com/twstock/2408",
    "title": "[放棄理由,未標記] 矽光子/CPO 於 2025-01-13 屬『造浪太早』:點火源(大摩「CPO 元年」報告 2025-01-16、NVIDIA GTC Quantum-X/Spectrum-X Photonics 2025-03)均在 t0 之後",
    "excerpt": "矽光子/CPO 為最高品質之休眠結構題材(上詮3363/聯亞3081/光聖6442/波若威3163 卡位 TSMC FAU/silicon photonics,結構事實 2023 起公開),但其 2025 再點火觸媒——大摩『CPO 元年』報告(2025-01-16)與 NVIDIA GTC(2025-03-18~21)發表 CPO 交換器——均落於 t0(2025-01-13)之後 3 天至 2 個月。於 t0 當日『龍頭/族群尚未動、無可事前識別之近端行事曆觸發』,判為造浪太早、conviction 3,列首要 watchlist 不標記。材料時齡與點火日取自本地庫 6442/3081 檔之 pre_t0 段。",
    "used": false
  },
  {
    "date": "2025(第二波標案 2025 下半年;川普就職 2025-01-20)",
    "source": "產業彙整(國防/無人機)",
    "url": "https://www.esunsec.com.tw/article/post/356",
    "title": "[放棄理由,未標記] 國防/無人機於 2025-01-13 屬『造浪太早』:第二波軍備局 4.8 萬架/700 億標案於 2025 下半年才開徵求案,川普就職(2025-01-20)亦在 t0 後",
    "excerpt": "台灣無人機第一波標案(3,600 架/70 億,中光電/長榮航太等)2024 已得標交貨;真正大單『第二波』(五機型 48,750 架、預算逾 700 億)於 2025 下半年才開徵求案,量產放量要 2026 下半年。川普就職(2025-01-20)、雷虎 Blue UAS 認證(2025-09)等均為 t0 後。於 2025-01-13 該題材無可事前識別之近端點火觸媒、兌現遠,判造浪太早,列 watchlist 不標記。",
    "used": false
  },
  {
    "date": "2024~2025-01(產業循環判讀)",
    "source": "研究員 PIT 題材地圖判讀(綜合當期產業狀態)",
    "url": "https://www.evergreen.local/theme-map/2025-01",
    "title": "[放棄理由,未標記] AI ASIC(世芯3661/創意3443)、散熱/液冷(奇鋐3017/雙鴻3324)、重電/電網(華城1519/中興電1513)、GB200 伺服器鏈於 2025-01 屬『已大漲/人盡皆知』;記憶體(DRAM)屬下行循環",
    "excerpt": "2025-01-13 主流 AI 子題材多已中後段:ASIC、散熱/液冷、重電/電網、CoWoS/GB200 伺服器鏈於 2024 已大漲、人盡皆知,無『未定價純受惠冷門股』,追之等於追高,依一票否決『招牌利多已見報且股價已大漲反映』棄權。記憶體 DRAM 於 2024 Q4 合約價下行(消費端庫存過剩),屬下行循環,棄權(HBM 為韓廠、非台股純受惠)。玻璃基板/CoPoS 之郭明錤『AI 必需品』論述為 2025-2026 post-PIT,亦造浪太早。此筆記錄棄權範圍,used=false。",
    "used": false
  }
]
