{
 "label_month": "2023-04",
 "label_day": "2023-04-06",
 "momentum_clusters": [
  {
   "industry": "半導體業",
   "members": [
    {
     "code": "4967",
     "ret60_pct": 129.9
    },
    {
     "code": "8227",
     "ret60_pct": 106.8
    },
    {
     "code": "6531",
     "ret60_pct": 90.0
    },
    {
     "code": "3675",
     "ret60_pct": 82.7
    },
    {
     "code": "6515",
     "ret60_pct": 79.0
    },
    {
     "code": "6799",
     "ret60_pct": 64.9
    },
    {
     "code": "6485",
     "ret60_pct": 59.8
    },
    {
     "code": "6732",
     "ret60_pct": 57.5
    },
    {
     "code": "5269",
     "ret60_pct": 56.9
    },
    {
     "code": "6548",
     "ret60_pct": 54.3
    },
    {
     "code": "6788",
     "ret60_pct": 54.0
    },
    {
     "code": "3661",
     "ret60_pct": 50.7
    }
   ]
  },
  {
   "industry": "資訊服務業",
   "members": [
    {
     "code": "6874",
     "ret60_pct": 199.5
    },
    {
     "code": "2453",
     "ret60_pct": 165.6
    },
    {
     "code": "6752",
     "ret60_pct": 119.3
    },
    {
     "code": "2471",
     "ret60_pct": 84.9
    },
    {
     "code": "6148",
     "ret60_pct": 67.6
    },
    {
     "code": "6811",
     "ret60_pct": 63.9
    },
    {
     "code": "5211",
     "ret60_pct": 50.8
    },
    {
     "code": "6231",
     "ret60_pct": 49.1
    }
   ]
  },
  {
   "industry": "電子零組件業",
   "members": [
    {
     "code": "5340",
     "ret60_pct": 85.0
    },
    {
     "code": "3624",
     "ret60_pct": 75.7
    },
    {
     "code": "3032",
     "ret60_pct": 55.5
    },
    {
     "code": "3078",
     "ret60_pct": 53.8
    },
    {
     "code": "3207",
     "ret60_pct": 53.0
    },
    {
     "code": "2402",
     "ret60_pct": 52.2
    },
    {
     "code": "2457",
     "ret60_pct": 50.2
    },
    {
     "code": "3338",
     "ret60_pct": 49.9
    }
   ]
  },
  {
   "industry": "電機機械",
   "members": [
    {
     "code": "2230",
     "ret60_pct": 159.1
    },
    {
     "code": "6122",
     "ret60_pct": 61.0
    },
    {
     "code": "1504",
     "ret60_pct": 56.3
    },
    {
     "code": "1519",
     "ret60_pct": 50.1
    },
    {
     "code": "8222",
     "ret60_pct": 48.9
    }
   ]
  },
  {
   "industry": "電腦及週邊設備業",
   "members": [
    {
     "code": "6235",
     "ret60_pct": 127.7
    },
    {
     "code": "5289",
     "ret60_pct": 76.6
    },
    {
     "code": "3594",
     "ret60_pct": 74.6
    },
    {
     "code": "6160",
     "ret60_pct": 56.7
    },
    {
     "code": "3046",
     "ret60_pct": 55.3
    }
   ]
  },
  {
   "industry": "通信網路業",
   "members": [
    {
     "code": "6417",
     "ret60_pct": 67.3
    },
    {
     "code": "3558",
     "ret60_pct": 64.8
    },
    {
     "code": "5353",
     "ret60_pct": 60.2
    },
    {
     "code": "3447",
     "ret60_pct": 54.1
    },
    {
     "code": "6143",
     "ret60_pct": 53.2
    }
   ]
  },
  {
   "industry": "生技醫療業",
   "members": [
    {
     "code": "6472",
     "ret60_pct": 98.8
    },
    {
     "code": "6612",
     "ret60_pct": 63.4
    },
    {
     "code": "4164",
     "ret60_pct": 59.7
    },
    {
     "code": "6733",
     "ret60_pct": 50.9
    }
   ]
  },
  {
   "industry": "光電業",
   "members": [
    {
     "code": "6517",
     "ret60_pct": 109.4
    },
    {
     "code": "3362",
     "ret60_pct": 49.8
    },
    {
     "code": "3563",
     "ret60_pct": 48.5
    }
   ]
  }
 ],
 "revenue_accel_clusters": [
  {
   "industry": "電機機械",
   "members": [
    {
     "code": "3162",
     "yoy_3m": 214.0,
     "yoy_3m_prev": 145.0
    },
    {
     "code": "8996",
     "yoy_3m": 78.0,
     "yoy_3m_prev": 49.0
    },
    {
     "code": "2371",
     "yoy_3m": 55.0,
     "yoy_3m_prev": 46.0
    },
    {
     "code": "4572",
     "yoy_3m": 74.0,
     "yoy_3m_prev": 58.0
    },
    {
     "code": "6122",
     "yoy_3m": 73.0,
     "yoy_3m_prev": 37.0
    },
    {
     "code": "1529",
     "yoy_3m": 140.0,
     "yoy_3m_prev": 33.0
    }
   ]
  },
  {
   "industry": "生技醫療業",
   "members": [
    {
     "code": "1762",
     "yoy_3m": 63.0,
     "yoy_3m_prev": 43.0
    },
    {
     "code": "4119",
     "yoy_3m": 156.0,
     "yoy_3m_prev": 57.0
    },
    {
     "code": "4142",
     "yoy_3m": 496.0,
     "yoy_3m_prev": -16.0
    },
    {
     "code": "6472",
     "yoy_3m": 379.0,
     "yoy_3m_prev": 344.0
    },
    {
     "code": "4123",
     "yoy_3m": 150.0,
     "yoy_3m_prev": 117.0
    },
    {
     "code": "6841",
     "yoy_3m": 266.0,
     "yoy_3m_prev": 265.0
    }
   ]
  },
  {
   "industry": "通信網路業",
   "members": [
    {
     "code": "6163",
     "yoy_3m": 88.0,
     "yoy_3m_prev": -4.0
    },
    {
     "code": "4979",
     "yoy_3m": 192.0,
     "yoy_3m_prev": 104.0
    },
    {
     "code": "8171",
     "yoy_3m": 106.0,
     "yoy_3m_prev": 88.0
    }
   ]
  },
  {
   "industry": "觀光餐旅",
   "members": [
    {
     "code": "2743",
     "yoy_3m": 998.0,
     "yoy_3m_prev": 266.0
    },
    {
     "code": "5706",
     "yoy_3m": 1171.0,
     "yoy_3m_prev": 170.0
    },
    {
     "code": "2731",
     "yoy_3m": 387.0,
     "yoy_3m_prev": 198.0
    }
   ]
  },
  {
   "industry": "電腦及週邊設備業",
   "members": [
    {
     "code": "4916",
     "yoy_3m": 89.0,
     "yoy_3m_prev": 70.0
    },
    {
     "code": "3693",
     "yoy_3m": 116.0,
     "yoy_3m_prev": 85.0
    },
    {
     "code": "3046",
     "yoy_3m": 51.0,
     "yoy_3m_prev": 4.0
    }
   ]
  }
 ]
}