{
 "label_month": "2024-08",
 "label_day": "2024-08-01",
 "momentum_clusters": [
  {
   "industry": "電機機械",
   "members": [
    {
     "code": "8374",
     "ret60_pct": 262.7
    },
    {
     "code": "3379",
     "ret60_pct": 221.3
    },
    {
     "code": "4562",
     "ret60_pct": 205.6
    },
    {
     "code": "4510",
     "ret60_pct": 106.5
    },
    {
     "code": "4534",
     "ret60_pct": 103.4
    },
    {
     "code": "2070",
     "ret60_pct": 89.5
    },
    {
     "code": "4566",
     "ret60_pct": 82.6
    },
    {
     "code": "4513",
     "ret60_pct": 69.7
    },
    {
     "code": "1540",
     "ret60_pct": 65.0
    }
   ]
  },
  {
   "industry": "其他電子業",
   "members": [
    {
     "code": "3580",
     "ret60_pct": 88.0
    },
    {
     "code": "3663",
     "ret60_pct": 83.4
    },
    {
     "code": "3665",
     "ret60_pct": 82.8
    },
    {
     "code": "2464",
     "ret60_pct": 81.9
    },
    {
     "code": "2359",
     "ret60_pct": 71.2
    },
    {
     "code": "2312",
     "ret60_pct": 63.6
    },
    {
     "code": "6658",
     "ret60_pct": 58.3
    },
    {
     "code": "5452",
     "ret60_pct": 55.7
    }
   ]
  },
  {
   "industry": "光電業",
   "members": [
    {
     "code": "3535",
     "ret60_pct": 244.9
    },
    {
     "code": "5484",
     "ret60_pct": 211.3
    },
    {
     "code": "2438",
     "ret60_pct": 205.2
    },
    {
     "code": "6706",
     "ret60_pct": 135.1
    },
    {
     "code": "8064",
     "ret60_pct": 107.9
    },
    {
     "code": "6419",
     "ret60_pct": 104.6
    },
    {
     "code": "5443",
     "ret60_pct": 87.4
    }
   ]
  },
  {
   "industry": "半導體業",
   "members": [
    {
     "code": "6895",
     "ret60_pct": 141.6
    },
    {
     "code": "8028",
     "ret60_pct": 117.5
    },
    {
     "code": "3374",
     "ret60_pct": 116.5
    },
    {
     "code": "6640",
     "ret60_pct": 107.3
    },
    {
     "code": "3450",
     "ret60_pct": 106.0
    },
    {
     "code": "3686",
     "ret60_pct": 63.8
    },
    {
     "code": "6788",
     "ret60_pct": 53.0
    }
   ]
  },
  {
   "industry": "通信網路業",
   "members": [
    {
     "code": "3047",
     "ret60_pct": 191.7
    },
    {
     "code": "6442",
     "ret60_pct": 182.0
    },
    {
     "code": "4903",
     "ret60_pct": 75.7
    },
    {
     "code": "6863",
     "ret60_pct": 60.5
    },
    {
     "code": "3163",
     "ret60_pct": 58.1
    },
    {
     "code": "8089",
     "ret60_pct": 56.6
    }
   ]
  },
  {
   "industry": "生技醫療業",
   "members": [
    {
     "code": "1799",
     "ret60_pct": 138.8
    },
    {
     "code": "6446",
     "ret60_pct": 117.8
    },
    {
     "code": "4160",
     "ret60_pct": 86.5
    },
    {
     "code": "1784",
     "ret60_pct": 75.4
    }
   ]
  },
  {
   "industry": "建材營造",
   "members": [
    {
     "code": "9906",
     "ret60_pct": 117.9
    },
    {
     "code": "2524",
     "ret60_pct": 87.6
    },
    {
     "code": "1438",
     "ret60_pct": 72.4
    },
    {
     "code": "3188",
     "ret60_pct": 54.7
    }
   ]
  },
  {
   "industry": "電子零組件業",
   "members": [
    {
     "code": "4545",
     "ret60_pct": 79.8
    },
    {
     "code": "6834",
     "ret60_pct": 62.6
    },
    {
     "code": "8103",
     "ret60_pct": 59.3
    },
    {
     "code": "3537",
     "ret60_pct": 53.2
    }
   ]
  },
  {
   "industry": "電腦及週邊設備業",
   "members": [
    {
     "code": "2365",
     "ret60_pct": 227.2
    },
    {
     "code": "3652",
     "ret60_pct": 62.9
    },
    {
     "code": "8114",
     "ret60_pct": 61.6
    }
   ]
  }
 ],
 "revenue_accel_clusters": [
  {
   "industry": "建材營造",
   "members": [
    {
     "code": "6219",
     "yoy_3m": 5387.0,
     "yoy_3m_prev": 3335.0
    },
    {
     "code": "1316",
     "yoy_3m": 171.0,
     "yoy_3m_prev": 14.0
    },
    {
     "code": "2542",
     "yoy_3m": 104.0,
     "yoy_3m_prev": -48.0
    },
    {
     "code": "2537",
     "yoy_3m": 51792.0,
     "yoy_3m_prev": 332.0
    },
    {
     "code": "3056",
     "yoy_3m": 110.0,
     "yoy_3m_prev": -4.0
    },
    {
     "code": "6186",
     "yoy_3m": 57001.0,
     "yoy_3m_prev": 950.0
    },
    {
     "code": "9946",
     "yoy_3m": 256.0,
     "yoy_3m_prev": 31.0
    },
    {
     "code": "5534",
     "yoy_3m": 335.0,
     "yoy_3m_prev": 19.0
    },
    {
     "code": "2539",
     "yoy_3m": 176.0,
     "yoy_3m_prev": -31.0
    },
    {
     "code": "1436",
     "yoy_3m": 2511.0,
     "yoy_3m_prev": 139.0
    },
    {
     "code": "2509",
     "yoy_3m": 948.0,
     "yoy_3m_prev": 10.0
    },
    {
     "code": "2520",
     "yoy_3m": 132.0,
     "yoy_3m_prev": 18.0
    },
    {
     "code": "2524",
     "yoy_3m": 276.0,
     "yoy_3m_prev": 126.0
    },
    {
     "code": "2538",
     "yoy_3m": 1053.0,
     "yoy_3m_prev": -33.0
    },
    {
     "code": "2548",
     "yoy_3m": 1776.0,
     "yoy_3m_prev": -100.0
    },
    {
     "code": "1808",
     "yoy_3m": 2269.0,
     "yoy_3m_prev": -69.0
    },
    {
     "code": "6177",
     "yoy_3m": 1244.0,
     "yoy_3m_prev": 248.0
    },
    {
     "code": "5522",
     "yoy_3m": 967.0,
     "yoy_3m_prev": -43.0
    },
    {
     "code": "4907",
     "yoy_3m": 605115.0,
     "yoy_3m_prev": 131012.0
    },
    {
     "code": "2528",
     "yoy_3m": 632.0,
     "yoy_3m_prev": -20.0
    },
    {
     "code": "4113",
     "yoy_3m": 218755.0,
     "yoy_3m_prev": 45102.0
    },
    {
     "code": "2530",
     "yoy_3m": 44878.0,
     "yoy_3m_prev": 19744.0
    }
   ]
  },
  {
   "industry": "通信網路業",
   "members": [
    {
     "code": "4903",
     "yoy_3m": 122.0,
     "yoy_3m_prev": -12.0
    },
    {
     "code": "3491",
     "yoy_3m": 76.0,
     "yoy_3m_prev": 3.0
    },
    {
     "code": "6163",
     "yoy_3m": 74.0,
     "yoy_3m_prev": -10.0
    },
    {
     "code": "8089",
     "yoy_3m": 510.0,
     "yoy_3m_prev": 47.0
    },
    {
     "code": "6863",
     "yoy_3m": 104.0,
     "yoy_3m_prev": 54.0
    },
    {
     "code": "3047",
     "yoy_3m": 100.0,
     "yoy_3m_prev": -15.0
    },
    {
     "code": "8011",
     "yoy_3m": 99.0,
     "yoy_3m_prev": 83.0
    },
    {
     "code": "6442",
     "yoy_3m": 105.0,
     "yoy_3m_prev": 30.0
    },
    {
     "code": "4909",
     "yoy_3m": 420.0,
     "yoy_3m_prev": 245.0
    }
   ]
  },
  {
   "industry": "生技醫療業",
   "members": [
    {
     "code": "4743",
     "yoy_3m": 59.0,
     "yoy_3m_prev": 29.0
    },
    {
     "code": "6550",
     "yoy_3m": 2286.0,
     "yoy_3m_prev": 1910.0
    },
    {
     "code": "6589",
     "yoy_3m": 80.0,
     "yoy_3m_prev": 4.0
    },
    {
     "code": "6841",
     "yoy_3m": 480.0,
     "yoy_3m_prev": 346.0
    },
    {
     "code": "6782",
     "yoy_3m": 72.0,
     "yoy_3m_prev": 62.0
    },
    {
     "code": "4162",
     "yoy_3m": 87.0,
     "yoy_3m_prev": -2.0
    },
    {
     "code": "4167",
     "yoy_3m": 65.0,
     "yoy_3m_prev": 15.0
    },
    {
     "code": "6472",
     "yoy_3m": 61.0,
     "yoy_3m_prev": -41.0
    }
   ]
  },
  {
   "industry": "電子零組件業",
   "members": [
    {
     "code": "2059",
     "yoy_3m": 92.0,
     "yoy_3m_prev": 67.0
    },
    {
     "code": "2467",
     "yoy_3m": 93.0,
     "yoy_3m_prev": 11.0
    },
    {
     "code": "6282",
     "yoy_3m": 60.0,
     "yoy_3m_prev": 39.0
    },
    {
     "code": "6207",
     "yoy_3m": 67.0,
     "yoy_3m_prev": 30.0
    },
    {
     "code": "6197",
     "yoy_3m": 65.0,
     "yoy_3m_prev": 38.0
    },
    {
     "code": "6274",
     "yoy_3m": 52.0,
     "yoy_3m_prev": 22.0
    },
    {
     "code": "6584",
     "yoy_3m": 71.0,
     "yoy_3m_prev": 42.0
    }
   ]
  },
  {
   "industry": "電機機械",
   "members": [
    {
     "code": "3379",
     "yoy_3m": 130.0,
     "yoy_3m_prev": -6.0
    },
    {
     "code": "6425",
     "yoy_3m": 204.0,
     "yoy_3m_prev": 166.0
    },
    {
     "code": "8027",
     "yoy_3m": 86.0,
     "yoy_3m_prev": -26.0
    },
    {
     "code": "1540",
     "yoy_3m": 114.0,
     "yoy_3m_prev": 15.0
    },
    {
     "code": "1529",
     "yoy_3m": 142.0,
     "yoy_3m_prev": -21.0
    },
    {
     "code": "3167",
     "yoy_3m": 92.0,
     "yoy_3m_prev": 58.0
    },
    {
     "code": "1532",
     "yoy_3m": 94.0,
     "yoy_3m_prev": 67.0
    }
   ]
  },
  {
   "industry": "其他電子業",
   "members": [
    {
     "code": "6187",
     "yoy_3m": 357.0,
     "yoy_3m_prev": 216.0
    },
    {
     "code": "6743",
     "yoy_3m": 75.0,
     "yoy_3m_prev": 27.0
    },
    {
     "code": "3324",
     "yoy_3m": 65.0,
     "yoy_3m_prev": -1.0
    },
    {
     "code": "3030",
     "yoy_3m": 87.0,
     "yoy_3m_prev": 43.0
    },
    {
     "code": "3663",
     "yoy_3m": 101.0,
     "yoy_3m_prev": 2.0
    },
    {
     "code": "6658",
     "yoy_3m": 61.0,
     "yoy_3m_prev": -5.0
    }
   ]
  },
  {
   "industry": "光電業",
   "members": [
    {
     "code": "2406",
     "yoy_3m": 220.0,
     "yoy_3m_prev": 50.0
    },
    {
     "code": "3691",
     "yoy_3m": 309.0,
     "yoy_3m_prev": 100.0
    },
    {
     "code": "3406",
     "yoy_3m": 96.0,
     "yoy_3m_prev": 58.0
    },
    {
     "code": "3535",
     "yoy_3m": 767.0,
     "yoy_3m_prev": -69.0
    },
    {
     "code": "5484",
     "yoy_3m": 94.0,
     "yoy_3m_prev": -11.0
    },
    {
     "code": "2489",
     "yoy_3m": 55.0,
     "yoy_3m_prev": 31.0
    }
   ]
  },
  {
   "industry": "其他",
   "members": [
    {
     "code": "8932",
     "yoy_3m": 70.0,
     "yoy_3m_prev": 34.0
    },
    {
     "code": "8936",
     "yoy_3m": 61.0,
     "yoy_3m_prev": 55.0
    },
    {
     "code": "3313",
     "yoy_3m": 149448.0,
     "yoy_3m_prev": 524.0
    },
    {
     "code": "9902",
     "yoy_3m": 833.0,
     "yoy_3m_prev": 282.0
    },
    {
     "code": "6901",
     "yoy_3m": 69.0,
     "yoy_3m_prev": -846.0
    },
    {
     "code": "3284",
     "yoy_3m": 55.0,
     "yoy_3m_prev": 46.0
    }
   ]
  },
  {
   "industry": "半導體業",
   "members": [
    {
     "code": "3228",
     "yoy_3m": 121.0,
     "yoy_3m_prev": 55.0
    },
    {
     "code": "6533",
     "yoy_3m": 55.0,
     "yoy_3m_prev": 6.0
    },
    {
     "code": "3680",
     "yoy_3m": 80.0,
     "yoy_3m_prev": 10.0
    },
    {
     "code": "5274",
     "yoy_3m": 99.0,
     "yoy_3m_prev": 51.0
    },
    {
     "code": "6788",
     "yoy_3m": 106.0,
     "yoy_3m_prev": 9.0
    }
   ]
  },
  {
   "industry": "電腦及週邊設備業",
   "members": [
    {
     "code": "3013",
     "yoy_3m": 93.0,
     "yoy_3m_prev": -4.0
    },
    {
     "code": "2376",
     "yoy_3m": 188.0,
     "yoy_3m_prev": 98.0
    },
    {
     "code": "3712",
     "yoy_3m": 85.0,
     "yoy_3m_prev": 39.0
    },
    {
     "code": "2365",
     "yoy_3m": 52.0,
     "yoy_3m_prev": 28.0
    }
   ]
  },
  {
   "industry": "航運業",
   "members": [
    {
     "code": "2636",
     "yoy_3m": 101.0,
     "yoy_3m_prev": 38.0
    },
    {
     "code": "2615",
     "yoy_3m": 56.0,
     "yoy_3m_prev": 9.0
    },
    {
     "code": "2603",
     "yoy_3m": 58.0,
     "yoy_3m_prev": 36.0
    }
   ]
  }
 ]
}